{"DownloadEvent":[{"count":1,"name":"Open-Transactions","owner":"da2ce7","language":"C++"},{"count":1,"name":"hawkthorne-journey","owner":"kyleconroy","language":"Lua"},{"count":1,"name":"Tangerine","owner":"Tangerine-Community","language":"JavaScript"}],"CommitCommentEvent":[{"count":4,"name":"netty","owner":"netty","language":"Java"},{"count":3,"name":"sadface","owner":"benlk","language":"Python"},{"count":2,"name":"TrinityCore","owner":"gc","language":"C++"},{"count":1,"name":"ECM","owner":"Iaccidentally","language":null},{"count":1,"name":"brickhu.github.com","owner":"brickhu","language":null}],"ForkEvent":[{"count":2,"name":"Spoon-Knife","owner":"octocat","language":null},{"count":2,"name":"django-watermark","owner":"codekoala","language":"Python"},{"count":1,"name":"backbone.layoutmanager","owner":"tbranyen","language":"JavaScript"},{"count":1,"name":"jshint","owner":"jshint","language":"JavaScript"},{"count":1,"name":"net-ssh","owner":"net-ssh","language":"Ruby"}],"PullRequestReviewCommentEvent":[{"count":1,"name":"usergroup","owner":"rubytij","language":"JavaScript"},{"count":1,"name":"bitcoin","owner":"bitcoin","language":"C++"},{"count":1,"name":"picard","owner":"musicbrainz","language":"Python"}],"PullRequestEvent":[{"count":4,"name":"Vanilla","owner":"SpoutDev","language":"Java"},{"count":4,"name":"loomio","owner":"enspiral","language":"Ruby"},{"count":2,"name":"evolution","owner":"sjstoelting","language":"PHP"},{"count":2,"name":"community","owner":"neo4j","language":"Java"},{"count":2,"name":"Salesmania","owner":"B2OJustin","language":"Java"}],"IssueCommentEvent":[{"count":5,"name":"carmen","owner":"jim","language":"Ruby"},{"count":4,"name":"hagfish","owner":"mfiers","language":"Python"},{"count":4,"name":"rails","owner":"rails","language":"Ruby"},{"count":4,"name":"team-5","owner":"aaltowebapps","language":"JavaScript"},{"count":3,"name":"core","owner":"kohana","language":"PHP"}],"IssuesEvent":[{"count":8,"name":"test-repo","owner":"Axbit","language":null},{"count":4,"name":"team-5","owner":"aaltowebapps","language":"JavaScript"},{"count":4,"name":"pixieengine.com","owner":"PixieEngine","language":"ActionScript"},{"count":3,"name":"Ushahidi_Android","owner":"ushahidi","language":"Java"},{"count":3,"name":"cukebins","owner":"paoloambrosio","language":"C++"}],"PushEvent":[{"count":19,"name":"PixieDust","owner":"PixieEngine","language":"JavaScript"},{"count":15,"name":"joomla-cms","owner":"mbabker","language":"PHP"},{"count":12,"name":"sengopal.github.com","owner":"sengopal","language":"Ruby"},{"count":12,"name":"notebook","owner":"rishabhsrao","language":"JavaScript"},{"count":11,"name":"min","owner":"wreviews","language":"PHP"}],"WatchEvent":[{"count":4,"name":"async","owner":"caolan","language":"JavaScript"},{"count":3,"name":"meteor","owner":"meteor","language":"JavaScript"},{"count":3,"name":"bootstrap","owner":"twitter","language":"JavaScript"},{"count":3,"name":"webwriter","owner":"icebeat","language":"JavaScript"},{"count":2,"name":"sspulltorefresh","owner":"samsoffes","language":"Objective-C"}]}